nops_metadata/__init__.py
nops_metadata/constants.py
nops_metadata/schema.py
nops_metadata/spark_schema.py
nops_metadata/tests/__init__.py
nops_metadata/tests/conftest.py
nops_metadata/tests/test_fetcher.py
nops_metadata/tests/test_schema.py
nops_metadata/utils.py
nops_metadata-0.4.12.dist-info/METADATA
nops_metadata-0.4.12.dist-info/WHEEL
nops_metadata-0.4.12.dist-info/RECORD
