Metadata-Version: 2.1
Name: nops-metadata
Version: 0.4.12
Summary: Metadata producer tooling used in nOps.io
Author: nOps Engineers
Author-email: eng@nops.io
Requires-Python: >=3.7,<4.0
Classifier: Programming Language :: Python :: 3
Classifier: Programming Language :: Python :: 3.7
Classifier: Programming Language :: Python :: 3.8
Classifier: Programming Language :: Python :: 3.9
Classifier: Programming Language :: Python :: 3.10
Classifier: Programming Language :: Python :: 3.11
Classifier: Programming Language :: Python :: 3.12
Requires-Dist: boto3 (>=1.17.102)
Requires-Dist: pydantic (>=1.8.0)
Requires-Dist: pyrsistent (>=0.17.3)
Requires-Dist: pyspark[sql] (==3.3.1)
